infi.projector_plugins.sync-0.0.7-py3.7-nspkg.pth
infi/projector_plugins/sync/__init__.py
infi/projector_plugins/sync/__version__.py
infi.projector_plugins.sync-0.0.7.dist-info/LICENSE
infi.projector_plugins.sync-0.0.7.dist-info/METADATA
infi.projector_plugins.sync-0.0.7.dist-info/WHEEL
infi.projector_plugins.sync-0.0.7.dist-info/entry_points.txt
infi.projector_plugins.sync-0.0.7.dist-info/namespace_packages.txt
infi.projector_plugins.sync-0.0.7.dist-info/top_level.txt
infi.projector_plugins.sync-0.0.7.dist-info/RECORD
