Metadata-Version: 2.1
Name: infi.projector-plugins.sync
Version: 0.0.7
Summary: projector plugin to sync repository to a remote host
Home-page: https://git.infinidat.com/host-opensource/infi.projector_plugins.sync
Author: Arnon Yaari
Author-email: arnony@infinidat.com
License: BSD
Platform: UNKNOWN
Classifier: Intended Audience :: Developers
Classifier: Intended Audience :: System Administrators
Classifier: License :: OSI Approved :: BSD License
Classifier: Operating System :: OS Independent
Classifier: Programming Language :: Python
Classifier: Programming Language :: Python :: 2
Classifier: Programming Language :: Python :: 3
Classifier: Topic :: Software Development :: Libraries :: Python Modules
Requires-Dist: setuptools
Requires-Dist: infi.pysync
